mpbc_vyfa_sf/__init__.py
mpbc_vyfa_sf/amplifier.py
mpbc_vyfa_sf/attributes.py
mpbc_vyfa_sf/enums.py
mpbc_vyfa_sf/exceptions.py
mpbc_vyfa_sf/py.typed
mpbc_vyfa_sf-0.2.0.dist-info/WHEEL
mpbc_vyfa_sf-0.2.0.dist-info/METADATA
mpbc_vyfa_sf-0.2.0.dist-info/RECORD
