Metadata-Version: 2.1
Name: mpbc-vyfa-sf
Version: 0.2.0
Summary: Python interface for a MPB VYFA amplifier
Home-page: https://github.com/ograsdijk/MPBC-VYFA-SF
License: MIT
Author: ograsdijk
Author-email: o.grasdijk@gmail.com
Requires-Python: >=3.9,<4.0
Classifier: License :: OSI Approved :: MIT License
Classifier: Programming Language :: Python :: 3
Classifier: Programming Language :: Python :: 3.9
Classifier: Programming Language :: Python :: 3.10
Requires-Dist: PyVISA (>=1.12.0,<2.0.0)
Project-URL: Repository, https://github.com/ograsdijk/MPBC-VYFA-SF
